{"type":"FeatureCollection","metadata":{"source_key":"dep_500yr_flood_fuel_storage_tank","source_name":"Maine DEP Sea Level Rise Study","source_url":"https://gis.maine.gov/mapservices/rest/services/dep/MaineDEPSeaLevelRiseStudy/MapServer/16","feature_count":5,"feature_cap":5},"features":[{"type":"Feature","id":1,"geometry":{"type":"Point","coordinates":[-69.74177596246899,44.36332445518432]},"properties":{"OBJECTID":1,"REGISTRATION_NUMBER":177,"TANK_NUMBER":2,"FACILITY_NAME":"PERFORMANCE FOOD GROUP INC","FACILITY_STREET_ADDRESS":"DALTON RD","FACILITY_LOCATION_TOWN":"AUGUSTA","TANK_MATERIAL":"F_GLASS_SEC_CONT_PETRO_ALCOHOL","TANK_ABOVE_BELOW":"B","TANK_STATUS":"ACTIVE","TANK_VOLUME":4000,"Notes":null}},{"type":"Feature","id":2,"geometry":{"type":"Point","coordinates":[-67.28192954299683,45.19062091269167]},"properties":{"OBJECTID":2,"REGISTRATION_NUMBER":11117,"TANK_NUMBER":6,"FACILITY_NAME":"HARDWICKES COUNTRY STORE","FACILITY_STREET_ADDRESS":"14 MAIN ST","FACILITY_LOCATION_TOWN":"CALAIS","TANK_MATERIAL":"DBL_WALLED_CP_STEEL","TANK_ABOVE_BELOW":"B","TANK_STATUS":"ACTIVE","TANK_VOLUME":10000,"Notes":null}},{"type":"Feature","id":3,"geometry":{"type":"Point","coordinates":[-67.28192954299683,45.19062091269167]},"properties":{"OBJECTID":3,"REGISTRATION_NUMBER":11117,"TANK_NUMBER":7,"FACILITY_NAME":"HARDWICKES COUNTRY STORE","FACILITY_STREET_ADDRESS":"14 MAIN ST","FACILITY_LOCATION_TOWN":"CALAIS","TANK_MATERIAL":"DBL_WALLED_CP_STEEL","TANK_ABOVE_BELOW":"B","TANK_STATUS":"ACTIVE","TANK_VOLUME":10000,"Notes":null}},{"type":"Feature","id":4,"geometry":{"type":"Point","coordinates":[-67.28192954299683,45.19062091269167]},"properties":{"OBJECTID":4,"REGISTRATION_NUMBER":11117,"TANK_NUMBER":5,"FACILITY_NAME":"HARDWICKES COUNTRY STORE","FACILITY_STREET_ADDRESS":"14 MAIN ST","FACILITY_LOCATION_TOWN":"CALAIS","TANK_MATERIAL":"DBL_WALLED_CP_STEEL","TANK_ABOVE_BELOW":"B","TANK_STATUS":"ACTIVE","TANK_VOLUME":10000,"Notes":null}},{"type":"Feature","id":5,"geometry":{"type":"Point","coordinates":[-70.97787291304434,44.116919485679986]},"properties":{"OBJECTID":5,"REGISTRATION_NUMBER":7716,"TANK_NUMBER":3,"FACILITY_NAME":"PETES GARAGE","FACILITY_STREET_ADDRESS":"82 N FRYBERG RD","FACILITY_LOCATION_TOWN":"FRYEBURG","TANK_MATERIAL":"DBL_WALLED_CP_STEEL","TANK_ABOVE_BELOW":"B","TANK_STATUS":"ACTIVE","TANK_VOLUME":6000,"Notes":null}}]}